{
    "position": 81,
    "name": "maplestory",
    "genre_list": [
        "MMORPG",
        "2D Platformer",
        "Loot",
        "Character Customization"
    ],
    "publisher": "Nexon America Inc.",
    "developer": "NEXON Korea Corporation",
    "prices": [
        "$0",
        "$0"
    ],
    "discount_percent": "0%",
    "weekly_positions": {
        "2024-2-13": 55,
        "2024-2-20": 33,
        "2024-2-27": 85,
        "2024-3-26": 94,
        "2024-4-16": 60,
        "2024-4-9": 88
    },
    "normal_price": "$0",
    "discount_price": "$0"
}